CHANGELOG.md
LICENSE
README.md
pgfutil/__init__.py
pgfutil/__main__.py
pgfutil/core.py
pgfutil/fonts.py
pgfutil/ui.py
pgfutil-0.0.1.dist-info/METADATA
pgfutil-0.0.1.dist-info/WHEEL
pgfutil-0.0.1.dist-info/licenses/LICENSE
pgfutil-0.0.1.dist-info/RECORD
