Metadata-Version: 2.1
Name: pgfutil
Version: 0.0.1
Summary: A bitmap font conversion and pixel editing utility for Pico Graphics
Project-URL: GitHub, https://www.github.com/gadgetoid/pgfutil
Project-URL: Homepage, https://www.gadgetoid.com
Author-email: Philip Howard <github@gadgetoid.com>
Maintainer-email: Philip Howard <github@gadgetoid.com>
License: MIT License
License-File: LICENSE
Keywords: Pi,Raspberry
Classifier: Development Status :: 4 - Beta
Classifier: Intended Audience :: Developers
Classifier: License :: OSI Approved :: MIT License
Classifier: Operating System :: POSIX :: Linux
Classifier: Programming Language :: Python :: 3
Classifier: Programming Language :: Python :: 3 :: Only
Classifier: Programming Language :: Python :: 3.7
Classifier: Programming Language :: Python :: 3.8
Classifier: Programming Language :: Python :: 3.9
Classifier: Programming Language :: Python :: 3.10
Classifier: Programming Language :: Python :: 3.11
Classifier: Topic :: Software Development
Classifier: Topic :: Software Development :: Libraries
Classifier: Topic :: System :: Hardware
Requires-Python: >=3.7
